README.md
pyproject.toml
ommx_openjij_adapter/__init__.py
ommx_openjij_adapter.egg-info/PKG-INFO
ommx_openjij_adapter.egg-info/SOURCES.txt
ommx_openjij_adapter.egg-info/dependency_links.txt
ommx_openjij_adapter.egg-info/requires.txt
ommx_openjij_adapter.egg-info/top_level.txt
tests/test_sample.py