Metadata-Version: 2.4
Name: ommx_openjij_adapter
Version: 2.3.4
Summary: OMMX Adapter for OpenJij.
Author-email: "Jij Inc." <info@j-ij.com>
Project-URL: Repository, https://github.com/Jij-Inc/ommx
Project-URL: Issues, https://github.com/Jij-Inc/ommx/issues
Classifier: Programming Language :: Python :: 3 :: Only
Classifier: Programming Language :: Python :: 3.10
Classifier: Programming Language :: Python :: 3.11
Classifier: Programming Language :: Python :: 3.12
Classifier: License :: OSI Approved :: Apache Software License
Classifier: License :: OSI Approved :: MIT License
Requires-Python: <3.14,>=3.10
Requires-Dist: ommx<3.0.0,>=2.0.0rc1
Requires-Dist: openjij<1.0.0,>=0.9.2
